cts_chamber/__init__.py
cts_chamber/_constants.py
cts_chamber/_cts_chamber.py
cts_chamber/_exceptions.py
cts_chamber/_ramp_parameters.py
cts_chamber/_state.py
cts_chamber/py.typed
cts_chamber-0.3.0.dist-info/METADATA
cts_chamber-0.3.0.dist-info/WHEEL
cts_chamber-0.3.0.dist-info/licenses/LICENSE.txt
cts_chamber-0.3.0.dist-info/RECORD
