Metadata-Version: 2.4
Name: cts-chamber
Version: 0.3.0
Summary: Control Interface for CTS Environmental Chambers
Project-URL: Homepage, https://cts-chamber-8923d6.pages.desy.de
Project-URL: Source, https://gitlab.desy.de/leandro.lanzieri/cts-chamber
Project-URL: Documentation, https://cts-chamber-8923d6.pages.desy.de
Project-URL: Changelog, https://cts-chamber-8923d6.pages.desy.de/changelog.html
Project-URL: Issues, https://gitlab.desy.de/leandro.lanzieri/cts-chamber/-/issues
Author-email: Leandro Lanzieri <leandro.lanzieri@desy.de>
License-Expression: GPL-3.0-or-later
License-File: LICENSE.txt
Classifier: Development Status :: 4 - Beta
Classifier: Programming Language :: Python
Requires-Python: >=3.10
Requires-Dist: pyserial
Requires-Dist: pyvisa
Requires-Dist: pyvisa-py
